cmdbase/__init__.py
cmdbase/_version.py
cmdbase/admin.py
cmdbase/apiviews.py
cmdbase/apps.py
cmdbase/bases.py
cmdbase/categories.py
cmdbase/commons.py
cmdbase/context_processors.py
cmdbase/displays.py
cmdbase/issues.py
cmdbase/middleware.py
cmdbase/models.py
cmdbase/recents.py
cmdbase/reports.py
cmdbase/searches.py
cmdbase/signal_handlers.py
cmdbase/urls.py
cmdbase/utils.py
cmdbase/views.py
cmdbase/locale/fr/LC_MESSAGES/django.mo
cmdbase/locale/fr/LC_MESSAGES/django.po
cmdbase/locale/ru/LC_MESSAGES/django.mo
cmdbase/locale/ru/LC_MESSAGES/django.po
cmdbase/management/commands/cmdbase_import.py
cmdbase/management/commands/cmdbase_report.py
cmdbase/management/commands/cmdbase_verify.py
cmdbase/migrations/0001_initial.py
cmdbase/migrations/0002_manual.py
cmdbase/migrations/__init__.py
cmdbase/migrations/0002_manual/0-general.sql
cmdbase/migrations/0002_manual/category.sql
cmdbase/migrations/0002_manual/issue.sql
cmdbase/migrations/0002_manual/prop.sql
cmdbase/migrations/0002_manual/report.sql
cmdbase/samples/categories.yml
cmdbase/samples/items.jsonc
cmdbase/site/asgi.py
cmdbase/site/settings.py
cmdbase/site/urls.py
cmdbase/site/wsgi.py
cmdbase/static/cmdbase/base.css
cmdbase/static/cmdbase/base.js
cmdbase/static/cmdbase/favicon.ico
cmdbase/static/cmdbase/logo-30px.png
cmdbase/static/cmdbase/search.css
cmdbase/static/cmdbase/search.js
cmdbase/templates/403.html
cmdbase/templates/cmdbase/_category_children_tree.html
cmdbase/templates/cmdbase/_item_or_category.html
cmdbase/templates/cmdbase/_messages.html
cmdbase/templates/cmdbase/_report_list_script.html
cmdbase/templates/cmdbase/about.html
cmdbase/templates/cmdbase/base.html
cmdbase/templates/cmdbase/base_site.html
cmdbase/templates/cmdbase/category.html
cmdbase/templates/cmdbase/index.html
cmdbase/templates/cmdbase/issue_list.html
cmdbase/templates/cmdbase/item.html
cmdbase/templates/cmdbase/item_issues.html
cmdbase/templates/cmdbase/item_properties.html
cmdbase/templates/cmdbase/item_relations.html
cmdbase-0.0.1a2.dist-info/METADATA
cmdbase-0.0.1a2.dist-info/WHEEL
cmdbase-0.0.1a2.dist-info/entry_points.txt
cmdbase-0.0.1a2.dist-info/top_level.txt
cmdbase-0.0.1a2.dist-info/RECORD
