Metadata-Version: 2.1
Name: cmdbase
Version: 0.0.1a2
Summary: Building blocks for a CMDB, leveraging Django and PostgreSql.
Author-email: Ipamo <dev@ipamo.net>
Project-URL: Homepage, https://gitlab.com/ipamo/cmdbase
Project-URL: Bug Tracker, https://gitlab.com/ipamo/cmdbase/issues
Keywords: cmdb
Classifier: Development Status :: 1 - Planning
Classifier: License :: OSI Approved :: MIT License
Classifier: Operating System :: OS Independent
Classifier: Programming Language :: Python :: 3.11
Requires-Python: >=3.11.2
Requires-Dist: cmdbase-utils
Requires-Dist: django
Requires-Dist: djangorestframework
Requires-Dist: django-filter
Requires-Dist: django-js-choices
Requires-Dist: pyyaml
Requires-Dist: psycopg
Provides-Extra: all
Requires-Dist: django-import-export ; extra == 'all'
